wink_sdk_affiliate_inventory/__init__.py
wink_sdk_affiliate_inventory/api_client.py
wink_sdk_affiliate_inventory/api_response.py
wink_sdk_affiliate_inventory/configuration.py
wink_sdk_affiliate_inventory/exceptions.py
wink_sdk_affiliate_inventory/py.typed
wink_sdk_affiliate_inventory/rest.py
wink_sdk_affiliate_inventory/api/__init__.py
wink_sdk_affiliate_inventory/api/customization_api.py
wink_sdk_affiliate_inventory/api/embeddable_inventories_api.py
wink_sdk_affiliate_inventory/api/grids_api.py
wink_sdk_affiliate_inventory/api/inventory_links_api.py
wink_sdk_affiliate_inventory/api/items_api.py
wink_sdk_affiliate_inventory/api/maps_api.py
wink_sdk_affiliate_inventory/api/ranked_grids_api.py
wink_sdk_affiliate_inventory/api/sellable_items_api.py
wink_sdk_affiliate_inventory/api/supplier_links_api.py
wink_sdk_affiliate_inventory/api/syndicated_item_api.py
wink_sdk_affiliate_inventory/models/__init__.py
wink_sdk_affiliate_inventory/models/advanced_map_configuration_affiliate.py
wink_sdk_affiliate_inventory/models/advanced_map_configuration_view_affiliate.py
wink_sdk_affiliate_inventory/models/boolean_response_affiliate.py
wink_sdk_affiliate_inventory/models/campaign_inventory_affiliate.py
wink_sdk_affiliate_inventory/models/child_affiliate.py
wink_sdk_affiliate_inventory/models/configurable_geo_json_circle_affiliate.py
wink_sdk_affiliate_inventory/models/configurable_geo_json_point_affiliate.py
wink_sdk_affiliate_inventory/models/configurable_geo_json_polygon_affiliate.py
wink_sdk_affiliate_inventory/models/configurable_geo_json_rectangle_affiliate.py
wink_sdk_affiliate_inventory/models/country_affiliate.py
wink_sdk_affiliate_inventory/models/country_lightweight_affiliate.py
wink_sdk_affiliate_inventory/models/create_advanced_map_configuration_syndication_entry_request_affiliate.py
wink_sdk_affiliate_inventory/models/create_inventory_map_syndication_entry_request_affiliate.py
wink_sdk_affiliate_inventory-0.0.57.dist-info/licenses/LICENSE
wink_sdk_affiliate_inventory-0.0.57.dist-info/METADATA
wink_sdk_affiliate_inventory-0.0.57.dist-info/WHEEL
wink_sdk_affiliate_inventory-0.0.57.dist-info/top_level.txt
wink_sdk_affiliate_inventory-0.0.57.dist-info/RECORD
